data_narasak/__init__.py
data_narasak/core.py
data_narasak/extract.py
data_narasak/report.py
data_narasak/transform.py
data_narasak/visualize.py
test/__init__.py
test/test_core.py
test/test_extract.py
test/test_report.py
test/test_transform.py
test/test_visualize.py
data_narasak-0.1.2.dist-info/METADATA
data_narasak-0.1.2.dist-info/WHEEL
data_narasak-0.1.2.dist-info/top_level.txt
data_narasak-0.1.2.dist-info/RECORD
