Metadata-Version: 2.4
Name: data_narasak
Version: 0.1.2
Summary: A Python package for data transformation and generating PDF reports with detailed analysis and visualizations.
Author: Kumaran Ravichandran
Author-email: kumaranravi3112003@gmail.com
Classifier: Programming Language :: Python :: 3.11
Classifier: Operating System :: OS Independent
Classifier: License :: OSI Approved :: MIT License
Classifier: Topic :: Scientific/Engineering :: Information Analysis
Requires-Python: >=3.7
Requires-Dist: pandas>=1.3.0
Requires-Dist: numpy>=1.21.0
Requires-Dist: matplotlib>=3.4.0
Requires-Dist: reportlab>=3.6.0
Requires-Dist: openpyxl>=3.0.0
Requires-Dist: seaborn
Requires-Dist: scikit-learn
Dynamic: author
Dynamic: author-email
Dynamic: classifier
Dynamic: description
Dynamic: description-content-type
Dynamic: requires-dist
Dynamic: requires-python
Dynamic: summary
